{
  "hash": "a2e5c431",
  "browserHash": "d62f1ba3",
  "optimized": {
    "@angular/common": {
      "src": "../../../../../node_modules/@angular/common/fesm2022/common.mjs",
      "file": "@angular_common.js",
      "fileHash": "01686dcc",
      "needsInterop": false
    },
    "@angular/core": {
      "src": "../../../../../node_modules/@angular/core/fesm2022/core.mjs",
      "file": "@angular_core.js",
      "fileHash": "f711f005",
      "needsInterop": false
    },
    "@angular/material/toolbar": {
      "src": "../../../../../node_modules/@angular/material/fesm2022/toolbar.mjs",
      "file": "@angular_material_toolbar.js",
      "fileHash": "2020cd76",
      "needsInterop": false
    },
    "@angular/platform-browser": {
      "src": "../../../../../node_modules/@angular/platform-browser/fesm2022/platform-browser.mjs",
      "file": "@angular_platform-browser.js",
      "fileHash": "7b88fd90",
      "needsInterop": false
    },
    "@angular/platform-browser/animations": {
      "src": "../../../../../node_modules/@angular/platform-browser/fesm2022/animations.mjs",
      "file": "@angular_platform-browser_animations.js",
      "fileHash": "6e276543",
      "needsInterop": false
    },
    "@angular/router": {
      "src": "../../../../../node_modules/@angular/router/fesm2022/router.mjs",
      "file": "@angular_router.js",
      "fileHash": "95fca7d3",
      "needsInterop": false
    }
  },
  "chunks": {
    "chunk-76BOX7TI": {
      "file": "chunk-76BOX7TI.js"
    },
    "chunk-MFPE4VZZ": {
      "file": "chunk-MFPE4VZZ.js"
    },
    "chunk-XUYKTPYR": {
      "file": "chunk-XUYKTPYR.js"
    },
    "chunk-UWMPAZLN": {
      "file": "chunk-UWMPAZLN.js"
    }
  }
}